Metadata-Version: 2.3
Name: mseep-zenml
Version: 0.84.0
Summary: ZenML: Write production-ready ML code.
License: Apache-2.0
Keywords: machine learning,production,pipeline,mlops,devops
Author: mseep
Author-email: support@skydeck.ai
Maintainer: mseep
Maintainer-email: support@skydeck.ai
Requires-Python: >=3.9,<3.13
Classifier: Development Status :: 4 - Beta
Classifier: Intended Audience :: Developers
Classifier: Intended Audience :: Science/Research
Classifier: Intended Audience :: System Administrators
Classifier: License :: OSI Approved :: Apache Software License
Classifier: Programming Language :: Python :: 3
Classifier: Programming Language :: Python :: 3.9
Classifier: Programming Language :: Python :: 3.10
Classifier: Programming Language :: Python :: 3.11
Classifier: Programming Language :: Python :: 3.12
Classifier: Programming Language :: Python :: 3 :: Only
Classifier: Topic :: Software Development :: Libraries :: Python Modules
Classifier: Topic :: System :: Distributed Computing
Classifier: Typing :: Typed
Provides-Extra: adlfs
Provides-Extra: azureml
Provides-Extra: connectors-aws
Provides-Extra: connectors-azure
Provides-Extra: connectors-gcp
Provides-Extra: connectors-kubernetes
Provides-Extra: dev
Provides-Extra: gcsfs
Provides-Extra: s3fs
Provides-Extra: sagemaker
Provides-Extra: secrets-aws
Provides-Extra: secrets-azure
Provides-Extra: secrets-gcp
Provides-Extra: secrets-hashicorp
Provides-Extra: server
Provides-Extra: templates
Provides-Extra: terraform
Provides-Extra: vertex
Requires-Dist: Jinja2 ; extra == "server"
Requires-Dist: adlfs (>=2021.10.0) ; extra == "adlfs"
Requires-Dist: alembic (>=1.8.1,<=1.15.2)
Requires-Dist: aws-profile-manager (>=0.5.0) ; extra == "connectors-aws"
Requires-Dist: azure-ai-ml (==1.23.1) ; extra == "azureml"
Requires-Dist: azure-identity (>=1.4.0) ; extra == "secrets-azure" or extra == "connectors-azure"
Requires-Dist: azure-keyvault-secrets (>=4.0.0) ; extra == "secrets-azure"
Requires-Dist: azure-mgmt-containerregistry (>=10.0.0) ; extra == "connectors-azure"
Requires-Dist: azure-mgmt-containerservice (>=20.0.0) ; extra == "connectors-azure"
Requires-Dist: azure-mgmt-resource (>=21.0.0) ; extra == "connectors-azure"
Requires-Dist: azure-mgmt-storage (>=20.0.0) ; extra == "connectors-azure"
Requires-Dist: azure-storage-blob (>=12.0.0) ; extra == "connectors-azure"
Requires-Dist: bandit (>=1.7.5,<2.0.0) ; extra == "dev"
Requires-Dist: bcrypt (==4.0.1)
Requires-Dist: boto3 (>=1.16.0) ; extra == "secrets-aws" or extra == "connectors-aws"
Requires-Dist: click (>=8.0.1,<8.1.8)
Requires-Dist: cloudpickle (>=2.0.0,<3)
Requires-Dist: copier (>=8.1.0) ; extra == "templates"
Requires-Dist: coverage[toml] (>=5.5,<6.0) ; extra == "dev"
Requires-Dist: darglint (>=1.8.1,<2.0.0) ; extra == "dev"
Requires-Dist: distro (>=1.6.0,<2.0.0)
Requires-Dist: docker (>=7.1.0,<7.2.0)
Requires-Dist: fastapi (>=0.100,<=0.115.8) ; extra == "server"
Requires-Dist: gcsfs (>=2022.11.0) ; extra == "gcsfs"
Requires-Dist: gitpython (>=3.1.18,<4.0.0)
Requires-Dist: google-cloud-aiplatform (>=1.34.0) ; extra == "vertex"
Requires-Dist: google-cloud-artifact-registry (>=1.11.3) ; extra == "connectors-gcp"
Requires-Dist: google-cloud-container (>=2.21.0) ; extra == "connectors-gcp"
Requires-Dist: google-cloud-pipeline-components (>=2.19.0) ; extra == "vertex"
Requires-Dist: google-cloud-secret-manager (>=2.12.5) ; extra == "secrets-gcp"
Requires-Dist: google-cloud-storage (>=2.9.0) ; extra == "connectors-gcp"
Requires-Dist: hvac (>=0.11.2) ; extra == "secrets-hashicorp"
Requires-Dist: hypothesis (>=6.43.1,<7.0.0) ; extra == "dev"
Requires-Dist: importlib_metadata (<=7.0.0) ; python_version < "3.10"
Requires-Dist: ipinfo (>=4.4.3) ; extra == "server"
Requires-Dist: itsdangerous (>=2.2.0,<2.3.0) ; extra == "server"
Requires-Dist: jinja2-time (>=0.2.0,<0.3.0) ; extra == "templates"
Requires-Dist: kfp (>=2.6.0) ; extra == "vertex"
Requires-Dist: kubernetes (>=18.20.0) ; extra == "connectors-kubernetes" or extra == "connectors-aws" or extra == "connectors-gcp" or extra == "connectors-azure"
Requires-Dist: maison (<2.0) ; extra == "dev"
Requires-Dist: mike (>=1.1.2,<2.0.0) ; extra == "dev"
Requires-Dist: mkdocs (>=1.6.1,<2.0.0) ; extra == "dev"
Requires-Dist: mkdocs-autorefs (>=1.4.0,<2.0.0) ; extra == "dev"
Requires-Dist: mkdocs-awesome-pages-plugin (>=2.10.1,<3.0.0) ; extra == "dev"
Requires-Dist: mkdocs-material (==9.6.8) ; extra == "dev"
Requires-Dist: mkdocstrings[python] (>=0.28.1,<0.29.0) ; extra == "dev"
Requires-Dist: mypy (==1.7.1) ; extra == "dev"
Requires-Dist: orjson (>=3.10.0,<3.11.0) ; extra == "server"
Requires-Dist: packaging (>=24.1)
Requires-Dist: passlib[bcrypt] (>=1.7.4,<1.8.0)
Requires-Dist: psutil (>=5.0.0)
Requires-Dist: pydantic (>=2.0,<2.11.2)
Requires-Dist: pydantic-settings
Requires-Dist: pyjwt[crypto] (==2.7.*) ; extra == "server"
Requires-Dist: pyment (>=0.3.3,<0.4.0) ; extra == "dev"
Requires-Dist: pymysql (>=1.1.1,<1.2.0)
Requires-Dist: pytest (>=7.4.0,<8.0.0) ; extra == "dev"
Requires-Dist: pytest-clarity (>=1.0.1,<2.0.0) ; extra == "dev"
Requires-Dist: pytest-instafail (>=0.5.0) ; extra == "dev"
Requires-Dist: pytest-mock (>=3.6.1,<4.0.0) ; extra == "dev"
Requires-Dist: pytest-randomly (>=3.10.1,<4.0.0) ; extra == "dev"
Requires-Dist: pytest-rerunfailures (>=13.0) ; extra == "dev"
Requires-Dist: pytest-split (>=0.8.1,<0.9.0) ; extra == "dev"
Requires-Dist: python-dateutil (>=2.8.1,<3.0.0)
Requires-Dist: python-multipart (>=0.0.9,<0.1.0) ; extra == "server"
Requires-Dist: pyyaml (>=6.0.1)
Requires-Dist: pyyaml-include (<2.0) ; extra == "templates"
Requires-Dist: requests (>=2.27.11,<3.0.0) ; extra == "connectors-azure"
Requires-Dist: rich[jupyter] (>=12.0.0)
Requires-Dist: ruff (>=0.1.7) ; extra == "templates" or extra == "dev"
Requires-Dist: s3fs (>=2022.11.0,!=2025.3.1) ; extra == "s3fs"
Requires-Dist: sagemaker (>=2.237.3) ; extra == "sagemaker"
Requires-Dist: secure (>=0.3.0,<0.4.0) ; extra == "server"
Requires-Dist: setuptools (>=70.0.0)
Requires-Dist: sqlalchemy (>=2.0.0,<3.0.0)
Requires-Dist: sqlalchemy_utils
Requires-Dist: sqlmodel (==0.0.18)
Requires-Dist: tldextract (>=5.1.0,<5.2.0) ; extra == "server"
Requires-Dist: tox (>=3.24.3,<4.0.0) ; extra == "dev"
Requires-Dist: types-Markdown (>=3.3.6,<4.0.0) ; extra == "dev"
Requires-Dist: types-Pillow (>=9.2.1,<10.0.0) ; extra == "dev"
Requires-Dist: types-PyMySQL (>=1.0.4,<2.0.0) ; extra == "dev"
Requires-Dist: types-PyYAML (>=6.0.0,<7.0.0) ; extra == "dev"
Requires-Dist: types-certifi (>=2021.10.8.0,<2022.0.0.0) ; extra == "dev"
Requires-Dist: types-croniter (>=1.0.2,<2.0.0) ; extra == "dev"
Requires-Dist: types-futures (>=3.3.1,<4.0.0) ; extra == "dev"
Requires-Dist: types-paramiko (>=3.4.0) ; extra == "dev"
Requires-Dist: types-passlib (>=1.7.7,<2.0.0) ; extra == "dev"
Requires-Dist: types-protobuf (>=3.18.0,<4.0.0) ; extra == "dev"
Requires-Dist: types-psutil (>=5.8.13,<6.0.0) ; extra == "dev"
Requires-Dist: types-python-dateutil (>=2.8.2,<3.0.0) ; extra == "dev"
Requires-Dist: types-python-slugify (>=5.0.2,<6.0.0) ; extra == "dev"
Requires-Dist: types-redis (>=4.1.19,<5.0.0) ; extra == "dev"
Requires-Dist: types-requests (>=2.27.11,<3.0.0) ; extra == "dev"
Requires-Dist: types-setuptools (>=57.4.2,<58.0.0) ; extra == "dev"
Requires-Dist: types-six (>=1.16.2,<2.0.0) ; extra == "dev"
Requires-Dist: types-termcolor (>=1.1.2,<2.0.0) ; extra == "dev"
Requires-Dist: typing-extensions (>=3.7.4) ; extra == "dev"
Requires-Dist: uvicorn[standard] (>=0.17.5) ; extra == "server"
Requires-Dist: yamlfix (>=1.16.0,<2.0.0) ; extra == "dev"
Project-URL: Documentation, https://docs.zenml.io
Project-URL: Homepage, https://zenml.io
Project-URL: Repository, https://github.com/zenml-io/zenml
